Independence_test/Independence_test.py
Independence_test/__init__.py
Independence_test-0.0.2.dist-info/DESCRIPTION.rst
Independence_test-0.0.2.dist-info/METADATA
Independence_test-0.0.2.dist-info/RECORD
Independence_test-0.0.2.dist-info/WHEEL
Independence_test-0.0.2.dist-info/metadata.json
Independence_test-0.0.2.dist-info/top_level.txt
