Metadata-Version: 2.0
Name: Independence-test
Version: 0.0.2
Summary: Time Series Independence test
Home-page: UNKNOWN
Author: Yili Peng
Author-email: yili_peng@outlook.com
License: UNKNOWN
Platform: UNKNOWN
